veri_agents_common/__init__.py
veri_agents_common/tools/__init__.py
veri_agents_common-0.1.5.dist-info/METADATA
veri_agents_common-0.1.5.dist-info/WHEEL
veri_agents_common-0.1.5.dist-info/RECORD
