Metadata-Version: 2.4
Name: veri-agents-common
Version: 0.1.5
Summary: Veritone Agents Toolkit: Common functionality
Author-email: Markus Toman <mtoman@veritone.com>, Teo Boley <tboley@veritone.com>
Requires-Python: >=3.12
Requires-Dist: langchain-core<0.4.0,>=0.3.0
Requires-Dist: langchain<0.4.0,>=0.3.0
Requires-Dist: pydantic>=2.11.3
Provides-Extra: docling
Requires-Dist: docling<3.0.0,>=2.15.1; extra == 'docling'
Requires-Dist: langchain-docling<0.3.0,>=0.2.0; extra == 'docling'
Provides-Extra: fastapi
Requires-Dist: fastapi[standard]<1.0.0,>=0.112.2; extra == 'fastapi'
Provides-Extra: fastembed
Requires-Dist: fastembed<1.0.0,>=0.4.1; extra == 'fastembed'
Provides-Extra: graphql
Requires-Dist: graphql-core>=3.2.4; extra == 'graphql'
Provides-Extra: langchain-openai
Requires-Dist: langchain-openai>=0.3.28; extra == 'langchain-openai'
Provides-Extra: langfuse
Requires-Dist: langfuse<3.0.0,>=2.47.0; extra == 'langfuse'
Provides-Extra: langgraph
Requires-Dist: langgraph>0.6.0; extra == 'langgraph'
Provides-Extra: lightrag
Requires-Dist: asyncpg>=0.30.0; extra == 'lightrag'
Requires-Dist: lightrag-hku>=1.3.6; extra == 'lightrag'
Requires-Dist: openai>=1.77.0; extra == 'lightrag'
Requires-Dist: transformers>=4.42.4; extra == 'lightrag'
Provides-Extra: polars
Requires-Dist: polars>=1.33.1; extra == 'polars'
Provides-Extra: qdrant
Requires-Dist: langchain-qdrant<1.0.0,>=0.1.4; extra == 'qdrant'
